{"site":"https://w1.faselhdxwatch.top/","network":"FaselHD","description":"Arabic streaming site offering movies, series, anime, and TV shows with translations.","popularity":{"monthly_visits":"67M+","source":"semrush.com"},"content":{"latest_releases":["Moana 2","Sonic the Hedgehog 3","Challengers","Godzilla x Kong: The New Empire","Tarot","Atlas"],"categories":["Foreign Films","Dubbed","Indian","Asian","Anime","Series","TV Programs"],"exclusive":"Fasel Plus (premium content)"},"notes":{"multiple_domains":["faselhds.center","faselhd.pro"],"legal_warning":"Potentially pirated content. Risk of legal or security issues. Do not share personal or financial info."},"legal_alternatives":[{"name":"Netflix","type":"Streaming platform with original and translated content"},{"name":"Shahid","type":"Arabic platform with drama and TV content"},{"name":"OSN+","type":"Offers global movie and series library"}]}